reftrace-0.6.0.dist-info/LICENSE
reftrace-0.6.0.dist-info/WHEEL
reftrace-0.6.0.dist-info/RECORD
reftrace-0.6.0.dist-info/top_level.txt
reftrace-0.6.0.dist-info/entry_points.txt
reftrace-0.6.0.dist-info/METADATA
reftrace/_version.py
reftrace/__init__.py
reftrace/cli/info.py
reftrace/cli/graph.py
reftrace/cli/__init__.py
reftrace/cli/main.py
reftrace/linting/__init__.py
reftrace/fixtures/rules.py
reftrace/fixtures/__init__.py
reftrace/graph/__init__.py
reftrace/bindings/module.py
reftrace/bindings/process.py
reftrace/bindings/libreftrace.so
reftrace/bindings/config_file.py
reftrace/bindings/lib.py
reftrace/proto/common_pb2.pyi
reftrace/proto/config_file_pb2.pyi
reftrace/proto/config_file_pb2.py
reftrace/proto/module_pb2.pyi
reftrace/proto/module_pb2.py
reftrace/proto/common_pb2.py
reftrace/directives/queue.py
reftrace/directives/tag.py
reftrace/directives/maxsubmitawait.py
reftrace/directives/maxretries.py
reftrace/directives/errorstrategy.py
reftrace/directives/cache.py
reftrace/directives/shell.py
reftrace/directives/machinetype.py
reftrace/directives/fair.py
reftrace/directives/memory.py
reftrace/directives/executor.py
reftrace/directives/clusteroptions.py
reftrace/directives/base.py
reftrace/directives/maxforks.py
reftrace/directives/unknown.py
reftrace/directives/maxerrors.py
reftrace/directives/stageoutmode.py
reftrace/directives/spack.py
reftrace/directives/conda.py
reftrace/directives/module.py
reftrace/directives/array.py
reftrace/directives/time.py
reftrace/directives/cpus.py
reftrace/directives/penv.py
reftrace/directives/scratch.py
reftrace/directives/afterscript.py
reftrace/directives/arch.py
reftrace/directives/containeroptions.py
reftrace/directives/publishdir.py
reftrace/directives/disk.py
reftrace/directives/debug.py
reftrace/directives/accelerator.py
reftrace/directives/ext.py
reftrace/directives/resourcelimits.py
reftrace/directives/container.py
reftrace/directives/__init__.py
reftrace/directives/resourcelabels.py
reftrace/directives/stageinmode.py
reftrace/directives/dynamic.py
reftrace/directives/label.py
reftrace/directives/pod.py
reftrace/directives/echo.py
reftrace/directives/storedir.py
