Metadata-Version: 2.2
Name: reftrace
Version: 0.6.0
Summary: Lint Nextflow pipelines in Python
Author-email: Andrew Stiles <andrew@reftrace.com>
License: Apache-2.0
Requires-Python: >=3.9
License-File: LICENSE
Requires-Dist: click>=8.0.0
Requires-Dist: matplotlib>=3.9.4
Requires-Dist: networkx>=3.2.1
Requires-Dist: protobuf>=5.29.2
Provides-Extra: dev
Requires-Dist: pytest; extra == "dev"
Requires-Dist: pytest-cov; extra == "dev"
